odoo10_addon_web_dialog_size-10.0.1.0.2-py2.7-nspkg.pth
odoo/addons/web_dialog_size/README.rst
odoo/addons/web_dialog_size/__init__.py
odoo/addons/web_dialog_size/__manifest__.py
odoo/addons/web_dialog_size/static/description/icon.png
odoo/addons/web_dialog_size/static/src/css/web_dialog_size.css
odoo/addons/web_dialog_size/static/src/js/web_dialog_size.js
odoo/addons/web_dialog_size/static/src/xml/web_dialog_size.xml
odoo/addons/web_dialog_size/templates/assets.xml
odoo10_addon_web_dialog_size-10.0.1.0.2.dist-info/DESCRIPTION.rst
odoo10_addon_web_dialog_size-10.0.1.0.2.dist-info/METADATA
odoo10_addon_web_dialog_size-10.0.1.0.2.dist-info/RECORD
odoo10_addon_web_dialog_size-10.0.1.0.2.dist-info/WHEEL
odoo10_addon_web_dialog_size-10.0.1.0.2.dist-info/metadata.json
odoo10_addon_web_dialog_size-10.0.1.0.2.dist-info/namespace_packages.txt
odoo10_addon_web_dialog_size-10.0.1.0.2.dist-info/top_level.txt
