Metadata-Version: 2.0
Name: odoo10-addon-web-dialog-size
Version: 10.0.1.0.2
Summary: A module that lets the user expand a
Home-page: http://acsone.eu
Author: ACSONE SA/NV, Therp BV, Siddharth Bhalgami,Tecnativa, Odoo Community Association (OCA)
Author-email: support@odoo-community.org
License: AGPL-3
Platform: UNKNOWN
Classifier: Programming Language :: Python
Classifier: Framework :: Odoo
Classifier: License :: OSI Approved :: GNU Affero General Public License v3
Requires-Python: ~=2.7
Requires-Dist: odoo (<10.1dev,>=10.0)
